mcp_seniverse_weather_galaxy/__init__.py
mcp_seniverse_weather_galaxy/__main__.py
mcp_seniverse_weather_galaxy/server.py
mcp_seniverse_weather_galaxy-0.4.0.dist-info/METADATA
mcp_seniverse_weather_galaxy-0.4.0.dist-info/WHEEL
mcp_seniverse_weather_galaxy-0.4.0.dist-info/entry_points.txt
mcp_seniverse_weather_galaxy-0.4.0.dist-info/licenses/LICENSE
mcp_seniverse_weather_galaxy-0.4.0.dist-info/RECORD
