Metadata-Version: 2.4
Name: mcp-seniverse-weather-galaxy
Version: 0.4.0
Summary: Add your description here
License-File: LICENSE
Requires-Python: >=3.12
Requires-Dist: mcp[cli]>=1.18.0
Requires-Dist: requests>=2.32.5
